my_project/__init__.py
my_project/module1.py
my_project/module2.py
my_src_project-0.1.4.dist-info/METADATA
my_src_project-0.1.4.dist-info/WHEEL
my_src_project-0.1.4.dist-info/top_level.txt
my_src_project-0.1.4.dist-info/RECORD
